app/__init__.py
app/models.py
app/urls.py
app/wsgi.py
app/migrations/0001_initial.py
app/migrations/0002_create_homepage.py
app/migrations/0003_auto_20211128_1641.py
app/migrations/__init__.py
app/settings/__init__.py
app/settings/base.py
app/settings/dev.py
app/settings/production.py
wagtail_lottie/__init__.py
wagtail_lottie/admin.py
wagtail_lottie/apps.py
wagtail_lottie/blocks.py
wagtail_lottie/constants.py
wagtail_lottie/exceptions.py
wagtail_lottie/lottie_zip_file.py
wagtail_lottie/models.py
wagtail_lottie/views.py
wagtail_lottie/wagtail_hooks.py
wagtail_lottie/widgets.py
wagtail_lottie/migrations/0001_initial.py
wagtail_lottie/migrations/0002_auto_20211202_1722.py
wagtail_lottie/migrations/0003_lottieanimation_title.py
wagtail_lottie/migrations/__init__.py
wagtail_lottie/static/wagtail_lottie/lottie-animation.js
wagtail_lottie/static/wagtail_lottie/lottie-player.js
wagtail_lottie/templates/modeladmin/wagtail_lottie/lottieanimation/create.html
wagtail_lottie/templates/modeladmin/wagtail_lottie/lottieanimation/edit.html
wagtail_lottie/templates/modeladmin/wagtail_lottie/lottieanimation/index.html
wagtail_lottie/templates/wagtail_lottie/lottie_animation.html
wagtail_lottie/templates/wagtail_lottie/homepage/site_summary_lottie_animation.html
wagtail_lottie/tests/__init__.py
wagtail_lottie/tests/_constants.py
wagtail_lottie/tests/test_admin_views.py
wagtail_lottie/tests/test_lottie_zip_file.py
wagtail_lottie-0.1.19.dist-info/LICENSE
wagtail_lottie-0.1.19.dist-info/METADATA
wagtail_lottie-0.1.19.dist-info/WHEEL
wagtail_lottie-0.1.19.dist-info/top_level.txt
wagtail_lottie-0.1.19.dist-info/RECORD
